dbots/__init__.py
dbots/client_filler.py
dbots/errors.py
dbots/eventhandler.py
dbots/http.py
dbots/poster.py
dbots/service.py
dbots-4.0.0.dist-info/LICENSE
dbots-4.0.0.dist-info/METADATA
dbots-4.0.0.dist-info/WHEEL
dbots-4.0.0.dist-info/top_level.txt
dbots-4.0.0.dist-info/RECORD
